configtpl/__init__.py
configtpl/env.py
configtpl/main.py
configtpl/jinja/__init__.py
configtpl/jinja/env_factory.py
configtpl/jinja/filters.py
configtpl/jinja/globals.py
configtpl/utils/__init__.py
configtpl/utils/dicts.py
configtpl-3.0.0.dist-info/METADATA
configtpl-3.0.0.dist-info/WHEEL
configtpl-3.0.0.dist-info/licenses/LICENSE
configtpl-3.0.0.dist-info/RECORD
