Metadata-Version: 2.4
Name: configtpl
Version: 3.0.0
Summary: Configuration builder which uses Jinja for dynamic configuration generation
Project-URL: Homepage, https://github.com/ignytis/configtpl_py
Author-email: Ignytis <155588001+ignytis@users.noreply.github.com>
License-Expression: MIT
License-File: LICENSE
Classifier: License :: OSI Approved :: MIT License
Classifier: Operating System :: OS Independent
Classifier: Programming Language :: Python :: 3
Classifier: Programming Language :: Python :: 3.11
Classifier: Programming Language :: Python :: 3.12
Classifier: Programming Language :: Python :: 3.13
Classifier: Programming Language :: Python :: 3.14
Requires-Python: >=3.11
Requires-Dist: jinja2<4.0.0,>=3.0.0
Provides-Extra: dev
Requires-Dist: hatch<1.17.0,>=1.16.0; extra == 'dev'
Requires-Dist: pre-commit; extra == 'dev'
Requires-Dist: pytest; extra == 'dev'
Requires-Dist: ruff==0.14.3; extra == 'dev'
Provides-Extra: yaml
Requires-Dist: pyyaml<7.0.0,>=5.1.1; extra == 'yaml'
